{
	"info": {
		"_postman_id": "d139cf13-453c-495c-a9c1-387e2e483a1c",
		"name": "Employee Management API",
		"schema": "https://schema.getpostman.com/json/collection/v2.1.0/collection.json",
		"_exporter_id": "32603171"
	},
	"item": [
		{
			"name": "Authentication",
			"item": [
				{
					"name": "Register",
					"request": {
						"method": "POST",
						"header": [],
						"body": {
							"mode": "raw",
							"raw": "{\r\n  \"username\": \"admin\",\r\n  \"email\": \"admin@example.com\",\r\n  \"password\": \"Admin@123\"\r\n}\r\n",
							"options": {
								"raw": {
									"language": "json"
								}
							}
						},
						"url": {
							"raw": "http://127.0.0.1:8000/api/auth/register/",
							"protocol": "http",
							"host": [
								"127",
								"0",
								"0",
								"1"
							],
							"port": "8000",
							"path": [
								"api",
								"auth",
								"register",
								""
							]
						}
					},
					"response": []
				},
				{
					"name": "Login",
					"request": {
						"method": "POST",
						"header": [],
						"body": {
							"mode": "raw",
							"raw": "{\r\n  \"username\": \"admin\",\r\n  \"password\": \"Admin@123\"\r\n}\r\n",
							"options": {
								"raw": {
									"language": "json"
								}
							}
						},
						"url": {
							"raw": "http://127.0.0.1:8000/api/token/",
							"protocol": "http",
							"host": [
								"127",
								"0",
								"0",
								"1"
							],
							"port": "8000",
							"path": [
								"api",
								"token",
								""
							]
						}
					},
					"response": []
				},
				{
					"name": "Profile",
					"request": {
						"auth": {
							"type": "bearer",
							"bearer": [
								{
									"key": "token",
									"value": "eyJhbGciOiJIUzI1NiIsInR5cCI6IkpXVCJ9.eyJ0b2tlbl90eXBlIjoiYWNjZXNzIiwiZXhwIjoxNzYwMTA0ODI0LCJpYXQiOjE3NjAxMDQ1MjQsImp0aSI6ImU5MWZkYzAzYjk2MTRlNzk4MzNmMjg2NjUyZTk1MzBkIiwidXNlcl9pZCI6IjEifQ.b8kRdwi-mG_DG2NtauuufqxnSJF4qxUEuKOutkdDHxw",
									"type": "string"
								}
							]
						},
						"method": "GET",
						"header": [],
						"url": {
							"raw": "http://127.0.0.1:8000/api/auth/profile/",
							"protocol": "http",
							"host": [
								"127",
								"0",
								"0",
								"1"
							],
							"port": "8000",
							"path": [
								"api",
								"auth",
								"profile",
								""
							]
						}
					},
					"response": []
				}
			]
		},
		{
			"name": "Forms",
			"item": [
				{
					"name": "Create Form Template",
					"request": {
						"auth": {
							"type": "bearer",
							"bearer": [
								{
									"key": "token",
									"value": "eyJhbGciOiJIUzI1NiIsInR5cCI6IkpXVCJ9.eyJ0b2tlbl90eXBlIjoiYWNjZXNzIiwiZXhwIjoxNzYwMTA0ODI0LCJpYXQiOjE3NjAxMDQ1MjQsImp0aSI6ImU5MWZkYzAzYjk2MTRlNzk4MzNmMjg2NjUyZTk1MzBkIiwidXNlcl9pZCI6IjEifQ.b8kRdwi-mG_DG2NtauuufqxnSJF4qxUEuKOutkdDHxw",
									"type": "string"
								}
							]
						},
						"method": "POST",
						"header": [],
						"body": {
							"mode": "raw",
							"raw": "{\r\n  \"name\": \"Employee Basic Form\",\r\n  \"fields\": [\r\n    {\"label\": \"Name\", \"type\": \"text\"},\r\n    {\"label\": \"Email\", \"type\": \"email\"},\r\n    {\"label\": \"DOB\", \"type\": \"date\"},\r\n    {\"label\": \"Salary\", \"type\": \"number\"}\r\n  ]\r\n}\r\n",
							"options": {
								"raw": {
									"language": "json"
								}
							}
						},
						"url": {
							"raw": "http://127.0.0.1:8000/api/forms/",
							"protocol": "http",
							"host": [
								"127",
								"0",
								"0",
								"1"
							],
							"port": "8000",
							"path": [
								"api",
								"forms",
								""
							]
						}
					},
					"response": []
				},
				{
					"name": "List All Forms",
					"request": {
						"auth": {
							"type": "bearer",
							"bearer": [
								{
									"key": "token",
									"value": "eyJhbGciOiJIUzI1NiIsInR5cCI6IkpXVCJ9.eyJ0b2tlbl90eXBlIjoiYWNjZXNzIiwiZXhwIjoxNzYwMTA0ODI0LCJpYXQiOjE3NjAxMDQ1MjQsImp0aSI6ImU5MWZkYzAzYjk2MTRlNzk4MzNmMjg2NjUyZTk1MzBkIiwidXNlcl9pZCI6IjEifQ.b8kRdwi-mG_DG2NtauuufqxnSJF4qxUEuKOutkdDHxw",
									"type": "string"
								}
							]
						},
						"method": "GET",
						"header": [],
						"url": {
							"raw": "http://127.0.0.1:8000/api/forms/",
							"protocol": "http",
							"host": [
								"127",
								"0",
								"0",
								"1"
							],
							"port": "8000",
							"path": [
								"api",
								"forms",
								""
							]
						}
					},
					"response": []
				}
			]
		},
		{
			"name": "Employee",
			"item": [
				{
					"name": "Create Employee",
					"request": {
						"auth": {
							"type": "bearer",
							"bearer": [
								{
									"key": "token",
									"value": "eyJhbGciOiJIUzI1NiIsInR5cCI6IkpXVCJ9.eyJ0b2tlbl90eXBlIjoiYWNjZXNzIiwiZXhwIjoxNzYwMTEyMTc5LCJpYXQiOjE3NjAxMDQ5NzksImp0aSI6ImMxYzEyNjk2MGRiYzRiMzliNDhlNzRmZTUwZTY3ODhkIiwidXNlcl9pZCI6IjEifQ.l9u87IscS3l-BMauKMCR-hsFLS_W0bILGJc2k_GD85c",
									"type": "string"
								}
							]
						},
						"method": "POST",
						"header": [],
						"body": {
							"mode": "raw",
							"raw": "{\r\n    \"form\": 1,\r\n    \"data\": {\r\n        \"Name\": \"Akshay Pk\",\r\n        \"Email\": \"akshay@example.com\",\r\n        \"DOB\": \"1999-08-12\",\r\n        \"Salary\": 50000\r\n    }\r\n}\r\n",
							"options": {
								"raw": {
									"language": "json"
								}
							}
						},
						"url": {
							"raw": "http://127.0.0.1:8000/api/employees/",
							"protocol": "http",
							"host": [
								"127",
								"0",
								"0",
								"1"
							],
							"port": "8000",
							"path": [
								"api",
								"employees",
								""
							]
						}
					},
					"response": []
				},
				{
					"name": "List Employee",
					"request": {
						"auth": {
							"type": "bearer",
							"bearer": [
								{
									"key": "token",
									"value": "eyJhbGciOiJIUzI1NiIsInR5cCI6IkpXVCJ9.eyJ0b2tlbl90eXBlIjoiYWNjZXNzIiwiZXhwIjoxNzYwMTEyMTc5LCJpYXQiOjE3NjAxMDQ5NzksImp0aSI6ImMxYzEyNjk2MGRiYzRiMzliNDhlNzRmZTUwZTY3ODhkIiwidXNlcl9pZCI6IjEifQ.l9u87IscS3l-BMauKMCR-hsFLS_W0bILGJc2k_GD85c",
									"type": "string"
								}
							]
						},
						"method": "GET",
						"header": [],
						"url": {
							"raw": "http://127.0.0.1:8000/api/employees/?search=aksh",
							"protocol": "http",
							"host": [
								"127",
								"0",
								"0",
								"1"
							],
							"port": "8000",
							"path": [
								"api",
								"employees",
								""
							],
							"query": [
								{
									"key": "search",
									"value": "aksh"
								}
							]
						}
					},
					"response": []
				},
				{
					"name": "Update Employee",
					"request": {
						"auth": {
							"type": "bearer",
							"bearer": [
								{
									"key": "token",
									"value": "eyJhbGciOiJIUzI1NiIsInR5cCI6IkpXVCJ9.eyJ0b2tlbl90eXBlIjoiYWNjZXNzIiwiZXhwIjoxNzYwMTEyMTc5LCJpYXQiOjE3NjAxMDQ5NzksImp0aSI6ImMxYzEyNjk2MGRiYzRiMzliNDhlNzRmZTUwZTY3ODhkIiwidXNlcl9pZCI6IjEifQ.l9u87IscS3l-BMauKMCR-hsFLS_W0bILGJc2k_GD85c",
									"type": "string"
								}
							]
						},
						"method": "PUT",
						"header": [],
						"body": {
							"mode": "raw",
							"raw": "{\r\n  \"data\": {\r\n        \"Name\": \"Akshay Pk\",\r\n        \"Email\": \"akshay@example.com\",\r\n        \"DOB\": \"1999-08-12\",\r\n        \"Salary\": 55000\r\n    }\r\n}\r\n",
							"options": {
								"raw": {
									"language": "json"
								}
							}
						},
						"url": {
							"raw": "http://127.0.0.1:8000/api/employees/1/",
							"protocol": "http",
							"host": [
								"127",
								"0",
								"0",
								"1"
							],
							"port": "8000",
							"path": [
								"api",
								"employees",
								"1",
								""
							]
						}
					},
					"response": []
				},
				{
					"name": "Delete Employee",
					"request": {
						"method": "DELETE",
						"header": [],
						"url": {
							"raw": "http://127.0.0.1:8000/api/employees/1/",
							"protocol": "http",
							"host": [
								"127",
								"0",
								"0",
								"1"
							],
							"port": "8000",
							"path": [
								"api",
								"employees",
								"1",
								""
							]
						}
					},
					"response": []
				}
			]
		}
	]
}